pygobuildinfo/__init__.py
pygobuildinfo/_pyGoBuildinfo.cpython-313-x86_64-linux-gnu.h
pygobuildinfo/_pyGoBuildinfo.cpython-313-x86_64-linux-gnu.so
pygobuildinfo/test_pyGoBuildInfo.py
pygobuildinfo/_pyinstaller/__init__.py
pygobuildinfo/_pyinstaller/hook-pygobuildinfo.py
pygobuildinfo-0.1.26.data/scripts/get_go_info
pygobuildinfo-0.1.26.dist-info/METADATA
pygobuildinfo-0.1.26.dist-info/WHEEL
pygobuildinfo-0.1.26.dist-info/entry_points.txt
pygobuildinfo-0.1.26.dist-info/top_level.txt
pygobuildinfo-0.1.26.dist-info/RECORD
pygobuildinfo-0.1.26.dist-info/licenses/LICENSE
