Metadata-Version: 2.4
Name: pygobuildinfo
Version: 0.1.26
Summary: A utility to extract go build info information fro go executables and shared libraries
Home-page: https://github.com/Mikemoore63/pybuildInfo
Author: Mike Moore
Author-email: z_z_zebra@yahoo.com
License: MIT
Classifier: Programming Language :: Python :: 3
Classifier: License :: OSI Approved :: MIT License
Classifier: Operating System :: OS Independent
License-File: LICENSE
Dynamic: license-file
